{"cat_name": "Бакалея", "cat_code": "870", "products": [{"id": 36, "name": "Дегидрированные продукты Vegeta Суп грибной с вермишелью 40г", "mech": null, "img_link": "https://media.5ka.ru/media/products/3977919.jpg", "plu": 3977919, "promo": {"id": 1163314563, "date_begin": "2021-02-28", "date_end": "2021-04-07", "type": "", "description": "", "kind": "Z011", "expired_at": 16}, "current_prices": {"price_reg__min": 34.49, "price_promo__min": 29.99}, "store_name": null}, {"id": 97, "name": "Изделия макаронные группа А, высший сорт, яичные: звездочки для супчика 250г", "mech": null, "img_link": "https://media.5ka.ru/media/products/4075782.jpg", "plu": 4075782, "promo": {"id": 1163314563, "date_begin": "2021-02-28", "date_end": "2021-04-07", "type": "", "description": "", "kind": "Z011", "expired_at": 16}, "current_prices": {"price_reg__min": 49.99, "price_promo__min": 34.99}, "store_name": null}, {"id": 23918, "name": "ДИАДАР Отруби хрустящие овсяные 200г", "mech": null, "img_link": "https://media.5ka.ru/media/products/3388018.jpg", "plu": 3388018, "promo": {"id": 1163314563, "date_begin": "2021-02-28", "date_end": "2021-04-07", "type": "", "description": "", "kind": "Z011", "expired_at": 16}, "current_prices": {"price_reg__min": 42.99, "price_promo__min": 34.99}, "store_name": null}, {"id": 23957, "name": "Соус Классический Thai-so, соевый, 250 мл", "mech": null, "img_link": "https://media.5ka.ru/media/products/3484963.jpg", "plu": 3484963, "promo": {"id": 1163314563, "date_begin": "2021-02-28", "date_end": "2021-04-07", "type": "", "description": "", "kind": "Z011", "expired_at": 16}, "current_prices": {"price_reg__min": 38.99, "price_promo__min": 34.99}, "store_name": null}, {"id": 23946, "name": "Цикорий Большая Чашка, классический, растворимый, 85 г", "mech": null, "img_link": "https://media.5ka.ru/media/products/3462819.jpg", "plu": 3462819, "promo": {"id": 1163314563, "date_begin": "2021-02-28", "date_end": "2021-04-07", "type": "", "description": "", "kind": "Z011", "expired_at": 16}, "current_prices": {"price_reg__min": 67.95, "price_promo__min": 39.99}, "store_name": null}, {"id": 23922, "name": "СЭН СОЙ Соус ТЕРИЯКИ ПРЕМИУМ столов.120г", "mech": null, "img_link": "https://media.5ka.ru/media/products/3408179.jpg", "plu": 3408179, "promo": {"id": 1163314563, "date_begin": "2021-02-28", "date_end": "2021-04-07", "type": "", "description": "", "kind": "Z011", "expired_at": 16}, "current_prices": {"price_reg__min": 44.99, "price_promo__min": 42.99}, "store_name": null}, {"id": 19787, "name": "Снеки хрустящие \"Луковые кольца Золотые\" со вкусом сметаны и лука, 100 гр", "mech": null, "img_link": "https://media.5ka.ru/media/products/3943730.jpg", "plu": 3943730, "promo": {"id": 1163236940, "date_begin": "2021-02-28", "date_end": "2021-04-03", "type": "", "description": "", "kind": "Z011", "expired_at": 12}, "current_prices": {"price_reg__min": 51.49, "price_promo__min": 44.99}, "store_name": null}, {"id": 26, "name": "Кетчуп первой категории Махеевъ \"Чили\" пакет ДОЙ-ПАК с дозатором 300 г", "mech": null, "img_link": "https://media.5ka.ru/media/products/3941585.jpg", "plu": 3941585, "promo": {"id": 1163314563, "date_begin": "2021-02-28", "date_end": "2021-04-07", "type": "", "description": "", "kind": "Z011", "expired_at": 16}, "current_prices": {"price_reg__min": 59.99, "price_promo__min": 45.99}, "store_name": null}, {"id": 76, "name": "Кетчуп Махеевъ \"Томатный\" Первая категория ДП 300г", "mech": null, "img_link": "https://media.5ka.ru/media/products/4044938.jpg", "plu": 4044938, "promo": {"id": 1163314563, "date_begin": "2021-02-28", "date_end": "2021-04-07", "type": "", "description": "", "kind": "Z011", "expired_at": 16}, "current_prices": {"price_reg__min": 59.99, "price_promo__min": 45.99}, "store_name": null}, {"id": 85, "name": "КУХМАСТЕР Соус \"Карри\" 260г.", "mech": null, "img_link": "https://media.5ka.ru/media/products/4064468.jpg", "plu": 4064468, "promo": {"id": 1163314563, "date_begin": "2021-02-28", "date_end": "2021-04-07", "type": "", "description": "", "kind": "Z011", "expired_at": 16}, "current_prices": {"price_reg__min": 69.99, "price_promo__min": 49.99}, "store_name": null}, {"id": 86, "name": "КУХМАСТЕР Соус \"Аджика\" 260г.", "mech": null, "img_link": "https://media.5ka.ru/media/products/4064470.jpg", "plu": 4064470, "promo": {"id": 1163314563, "date_begin": "2021-02-28", "date_end": "2021-04-07", "type": "", "description": "", "kind": "Z011", "expired_at": 16}, "current_prices": {"price_reg__min": 69.99, "price_promo__min": 49.99}, "store_name": null}, {"id": 14485, "name": "Томатный кетчуп Heinz 342г", "mech": null, "img_link": "https://media.5ka.ru/media/products/4086400.jpg", "plu": 4086400, "promo": {"id": 1166715645, "date_begin": "2021-03-07", "date_end": "2021-04-07", "type": "", "description": "", "kind": "Z011", "expired_at": 16}, "current_prices": {"price_reg__min": 99.99, "price_promo__min": 59.99}, "store_name": null}, {"id": 19703, "name": "DELICAD.Чипсы НАЧОС кукур.ориг.150г", "mech": null, "img_link": "https://media.5ka.ru/media/products/3463551.jpg", "plu": 3463551, "promo": {"id": 1163236940, "date_begin": "2021-02-28", "date_end": "2021-04-03", "type": "", "description": "", "kind": "Z011", "expired_at": 12}, "current_prices": {"price_reg__min": 67.99, "price_promo__min": 59.99}, "store_name": null}, {"id": 19704, "name": "DELICAD.Чипсы НАЧОС кукур.с/вк.сыр 150г", "mech": null, "img_link": "https://media.5ka.ru/media/products/3463552.jpg", "plu": 3463552, "promo": {"id": 1163236940, "date_begin": "2021-02-28", "date_end": "2021-04-03", "type": "", "description": "", "kind": "Z011", "expired_at": 12}, "current_prices": {"price_reg__min": 67.99, "price_promo__min": 59.99}, "store_name": null}, {"id": 19824, "name": "Ухтышки Сухие завтраки глазированные Шарики со вкусом шоколада 250г", "mech": null, "img_link": "https://media.5ka.ru/media/products/4030128.jpg", "plu": 4030128, "promo": {"id": 1163236940, "date_begin": "2021-02-28", "date_end": "2021-04-03", "type": "", "description": "", "kind": "Z011", "expired_at": 12}, "current_prices": {"price_reg__min": 64.99, "price_promo__min": 59.99}, "store_name": null}, {"id": 23952, "name": "УВЕЛКА Хлопья гречневые 400г", "mech": null, "img_link": "https://media.5ka.ru/media/products/3477319.jpg", "plu": 3477319, "promo": {"id": 1163314563, "date_begin": "2021-02-28", "date_end": "2021-04-07", "type": "", "description": "", "kind": "Z011", "expired_at": 16}, "current_prices": {"price_reg__min": 68.0, "price_promo__min": 59.99}, "store_name": null}, {"id": 19757, "name": "Чипсы Lays, лисички в сметане, 85 г", "mech": null, "img_link": "https://media.5ka.ru/media/products/3671742.jpg", "plu": 3671742, "promo": {"id": 1163236940, "date_begin": "2021-02-28", "date_end": "2021-04-03", "type": "", "description": "", "kind": "Z011", "expired_at": 12}, "current_prices": {"price_reg__min": 69.99, "price_promo__min": 64.99}, "store_name": null}, {"id": 19758, "name": "LAYS Чипсы карт.со вкус.неж.сыр зел.85г", "mech": null, "img_link": "https://media.5ka.ru/media/products/3671743.jpg", "plu": 3671743, "promo": {"id": 1163236940, "date_begin": "2021-02-28", "date_end": "2021-04-03", "type": "", "description": "", "kind": "Z011", "expired_at": 12}, "current_prices": {"price_reg__min": 69.99, "price_promo__min": 64.99}, "store_name": null}, {"id": 19782, "name": "Картофельные Чипсы Lay's со вкусом \"Королевский краб\" 85г", "mech": null, "img_link": "https://media.5ka.ru/media/products/3931228.jpg", "plu": 3931228, "promo": {"id": 1163236940, "date_begin": "2021-02-28", "date_end": "2021-04-03", "type": "", "description": "", "kind": "Z011", "expired_at": 12}, "current_prices": {"price_reg__min": 74.99, "price_promo__min": 64.99}, "store_name": null}, {"id": 66, "name": "Макаронные изделия из твердых сортов пшеницы группа А, высший сорт, Barilla, КАПЕЛЛИНИ 450 г.", "mech": null, "img_link": "https://media.5ka.ru/media/products/4037645.jpg", "plu": 4037645, "promo": {"id": 1163314563, "date_begin": "2021-02-28", "date_end": "2021-04-07", "type": "", "description": "", "kind": "Z011", "expired_at": 16}, "current_prices": {"price_reg__min": 89.99, "price_promo__min": 66.99}, "store_name": null}, {"id": 67, "name": "Макаронные изделия из твердых сортов пшеницы группа А, высший сорт, Barilla,ПЕННЕ РИГАТЕ 450г", "mech": null, "img_link": "https://media.5ka.ru/media/products/4037652.jpg", "plu": 4037652, "promo": {"id": 1163314563, "date_begin": "2021-02-28", "date_end": "2021-04-07", "type": "", "description": "", "kind": "Z011", "expired_at": 16}, "current_prices": {"price_reg__min": 89.99, "price_promo__min": 66.99}, "store_name": null}, {"id": 68, "name": "Макаронные изделия из твердых сортов пшеницы группа А, высший сорт, Barilla,ПИПЕ РИГАТЕ 450г", "mech": null, "img_link": "https://media.5ka.ru/media/products/4037654.jpg", "plu": 4037654, "promo": {"id": 1163314563, "date_begin": "2021-02-28", "date_end": "2021-04-07", "type": "", "description": "", "kind": "Z011", "expired_at": 16}, "current_prices": {"price_reg__min": 89.99, "price_promo__min": 66.99}, "store_name": null}, {"id": 64, "name": "Набор для приготовления \"Паста \"Портобелло\" в грибном соусе\" \"Увелка\" 0,34 кг", "mech": null, "img_link": "https://media.5ka.ru/media/products/4027518.jpg", "plu": 4027518, "promo": {"id": 1163314563, "date_begin": "2021-02-28", "date_end": "2021-04-07", "type": "", "description": "", "kind": "Z011", "expired_at": 16}, "current_prices": {"price_reg__min": 89.99, "price_promo__min": 69.99}, "store_name": null}, {"id": 19741, "name": "Хлопья зерновые \"Мультизлаковые\" 1/250 ц/п (ТМ \"Любятово\")", "mech": null, "img_link": "https://media.5ka.ru/media/products/3635443.jpg", "plu": 3635443, "promo": {"id": 1163236940, "date_begin": "2021-02-28", "date_end": "2021-04-03", "type": "", "description": "", "kind": "Z011", "expired_at": 12}, "current_prices": {"price_reg__min": 77.99, "price_promo__min": 69.99}, "store_name": null}, {"id": 19806, "name": "Майонез Классический, Heinz, 67%, 350 г", "mech": null, "img_link": "https://media.5ka.ru/media/products/4002440.jpg", "plu": 4002440, "promo": {"id": 1163236940, "date_begin": "2021-02-28", "date_end": "2021-04-03", "type": "", "description": "", "kind": "Z011", "expired_at": 12}, "current_prices": {"price_reg__min": 84.99, "price_promo__min": 69.99}, "store_name": null}, {"id": 19683, "name": "ОГО Завтраки МЮСЛИ зап.сух.с троп.фр350г", "mech": null, "img_link": "https://media.5ka.ru/media/products/3417240.jpg", "plu": 3417240, "promo": {"id": 1163236940, "date_begin": "2021-02-28", "date_end": "2021-04-03", "type": "", "description": "", "kind": "Z011", "expired_at": 12}, "current_prices": {"price_reg__min": 89.0, "price_promo__min": 79.99}, "store_name": null}, {"id": 19799, "name": "Майонез \"Московский Провансаль\" оливковый, массовая доля жира 67% 600мл.", "mech": null, "img_link": "https://media.5ka.ru/media/products/3982578.jpg", "plu": 3982578, "promo": {"id": 1163236940, "date_begin": "2021-02-28", "date_end": "2021-04-03", "type": "", "description": "", "kind": "Z011", "expired_at": 12}, "current_prices": {"price_reg__min": 109.99, "price_promo__min": 99.99}, "store_name": null}, {"id": 23853, "name": "KOTANYI Приправа ИТАЛ.ТР.в мельн.48г", "mech": null, "img_link": "https://media.5ka.ru/media/products/67129.jpg", "plu": 67129, "promo": {"id": 1163314563, "date_begin": "2021-02-28", "date_end": "2021-04-07", "type": "", "description": "", "kind": "Z011", "expired_at": 16}, "current_prices": {"price_reg__min": 106.6, "price_promo__min": 99.99}, "store_name": null}, {"id": 23860, "name": "KOTANYI Приправа 4 ПЕРЦА в мельн.35г", "mech": null, "img_link": "https://media.5ka.ru/media/products/89000.jpg", "plu": 89000, "promo": {"id": 1163314563, "date_begin": "2021-02-28", "date_end": "2021-04-07", "type": "", "description": "", "kind": "Z011", "expired_at": 16}, "current_prices": {"price_reg__min": 109.3, "price_promo__min": 99.99}, "store_name": null}, {"id": 23866, "name": "Приправа Kotanyi Чеснок-травы-соль 50г", "mech": null, "img_link": "https://media.5ka.ru/media/products/2058397.jpg", "plu": 2058397, "promo": {"id": 1163314563, "date_begin": "2021-02-28", "date_end": "2021-04-07", "type": "", "description": "", "kind": "Z011", "expired_at": 16}, "current_prices": {"price_reg__min": 109.3, "price_promo__min": 99.99}, "store_name": null}, {"id": 19653, "name": "AXA Мюсли медовые с ягодами 270г", "mech": null, "img_link": "https://media.5ka.ru/media/products/3224452.jpg", "plu": 3224452, "promo": {"id": 1163236940, "date_begin": "2021-02-28", "date_end": "2021-04-03", "type": "", "description": "", "kind": "Z011", "expired_at": 12}, "current_prices": {"price_reg__min": 169.99, "price_promo__min": 129.99}, "store_name": null}, {"id": 19716, "name": "AXA Мюсли медов.шокол/орех 250г", "mech": null, "img_link": "https://media.5ka.ru/media/products/3492142.jpg", "plu": 3492142, "promo": {"id": 1163236940, "date_begin": "2021-02-28", "date_end": "2021-04-03", "type": "", "description": "", "kind": "Z011", "expired_at": 12}, "current_prices": {"price_reg__min": 169.99, "price_promo__min": 129.99}, "store_name": null}, {"id": 11453, "name": "Рисовые чипсы Pringles \"Asian Collection\" со вкусом \"Соуса барбекю терияки по-японски\", 160 гр", "mech": null, "img_link": "https://media.5ka.ru/media/products/3994660.jpg", "plu": 3994660, "promo": {"id": 1165120646, "date_begin": "2021-03-07", "date_end": "2021-04-03", "type": "", "description": "", "kind": "Z011", "expired_at": 12}, "current_prices": {"price_reg__min": 199.99, "price_promo__min": 139.99}, "store_name": null}, {"id": 101, "name": "Масло оливковое нераф. Extra Virgin, ТМ «Global Village», 250мл", "mech": null, "img_link": "https://media.5ka.ru/media/products/4082388.jpg", "plu": 4082388, "promo": {"id": 1163314563, "date_begin": "2021-02-28", "date_end": "2021-04-07", "type": "", "description": "", "kind": "Z011", "expired_at": 16}, "current_prices": {"price_reg__min": 189.99, "price_promo__min": 169.99}, "store_name": null}]}